{
    "brim_ears_max_angle": "180",
    "brim_type": "no_brim",
    "brim_width": "10",
    "enable_support": "1",
    "from": "User",
    "inherits": "0.24mm Draft @Creality Ender3V2",
    "is_custom_defined": "0",
    "name": "0.24mm",
    "overhang_2_4_speed": "18",
    "overhang_3_4_speed": "13",
    "overhang_4_4_speed": "8",
    "print_settings_id": "0.24mm",
    "seam_position": "nearest",
    "skirt_distance": "10",
    "skirt_height": "3",
    "skirt_loops": "0",
    "sparse_infill_density": "10%",
    "sparse_infill_pattern": "supportcubic",
    "support_on_build_plate_only": "1",
    "support_style": "organic",
    "support_type": "tree(auto)",
    "top_shell_layers": "3",
    "version": "2.2.0.4",
    "wall_sequence": "inner-outer-inner wall"
}
